Blockthon/Bitcoin.py
Blockthon/BitcoinGold.py
Blockthon/Check.py
Blockthon/Dash.py
Blockthon/Digibyte.py
Blockthon/Dogecoin.py
Blockthon/Ethereum.py
Blockthon/Litecoin.py
Blockthon/Qtum.py
Blockthon/Ravencoin.py
Blockthon/Tron.py
Blockthon/Utils.py
Blockthon/Wallet.py
Blockthon/__init__.py
Blockthon/lib.py
Blockthon/zCash.py
Blockthon-7.9.3.dist-info/METADATA
Blockthon-7.9.3.dist-info/WHEEL
Blockthon-7.9.3.dist-info/top_level.txt
Blockthon-7.9.3.dist-info/RECORD
