Metadata-Version: 2.1
Name: Blockthon
Version: 7.9.3
Summary: Blockthon: Fast and easy generation of Private Keys and Mnemonics, converting Seed, Binary, and Decimal.
Home-page: https://github.com/Blockthon/Blockthon
Author: Pymmdrza
Author-email: Pymmdrza@gmail.com
Project-URL: Documentation, https://blockthon.github.io/Blockthon/
Project-URL: Personal Website, https://mmdrza.com
Project-URL: Example, https://github.com/Blockthon/Blockthon/tree/main/Example
Keywords: blockthon,bitcoin,ethereum,tron,dogecoin,dash,qtum,litecoin,bitcoingold,wallet,private key,mnemonic,seed,binary,hex,hunter,compress,un compress,compress address,un compress address
Classifier: Programming Language :: Python :: 3
Classifier: License :: OSI Approved :: MIT License
Classifier: Operating System :: OS Independent
Requires-Python: >=3.6
Requires-Dist: bit (==0.8.0)
Requires-Dist: hdwallet (==2.2.1)
Requires-Dist: requests (==2.28.2)
Requires-Dist: requests-html (==0.10.0)
Requires-Dist: ecdsa (==0.18.0)
Requires-Dist: bip-utils (==2.7.1)
Requires-Dist: bip32utils (==0.3.post4)
Requires-Dist: pycryptodome (==3.18.0)
Requires-Dist: pbkdf2 (==1.3)
Requires-Dist: base58 (==2.1.1)
